{
  "best_global_step": null,
  "best_metric": null,
  "best_model_checkpoint": null,
  "epoch": 1.0,
  "eval_steps": 50,
  "global_step": 115,
  "is_hyper_param_search": false,
  "is_local_process_zero": true,
  "is_world_process_zero": true,
  "log_history": [
    {
      "epoch": 0.008705114254624592,
      "grad_norm": 0.5303104519844055,
      "learning_rate": 0.0,
      "loss": 1.3242,
      "step": 1
    },
    {
      "epoch": 0.017410228509249184,
      "grad_norm": 0.3276662230491638,
      "learning_rate": 2e-05,
      "loss": 1.3192,
      "step": 2
    },
    {
      "epoch": 0.026115342763873776,
      "grad_norm": 0.3600560426712036,
      "learning_rate": 4e-05,
      "loss": 1.2565,
      "step": 3
    },
    {
      "epoch": 0.03482045701849837,
      "grad_norm": 0.37987783551216125,
      "learning_rate": 6e-05,
      "loss": 1.4592,
      "step": 4
    },
    {
      "epoch": 0.04352557127312296,
      "grad_norm": 0.3972161114215851,
      "learning_rate": 8e-05,
      "loss": 1.1138,
      "step": 5
    },
    {
      "epoch": 0.05223068552774755,
      "grad_norm": 0.38599950075149536,
      "learning_rate": 0.0001,
      "loss": 1.3398,
      "step": 6
    },
    {
      "epoch": 0.060935799782372145,
      "grad_norm": 0.4569900929927826,
      "learning_rate": 0.00012,
      "loss": 1.3471,
      "step": 7
    },
    {
      "epoch": 0.06964091403699674,
      "grad_norm": 0.4846457540988922,
      "learning_rate": 0.00014,
      "loss": 1.2813,
      "step": 8
    },
    {
      "epoch": 0.07834602829162132,
      "grad_norm": 0.5280914306640625,
      "learning_rate": 0.00016,
      "loss": 1.1164,
      "step": 9
    },
    {
      "epoch": 0.08705114254624592,
      "grad_norm": 0.6056145429611206,
      "learning_rate": 0.00018,
      "loss": 1.2738,
      "step": 10
    },
    {
      "epoch": 0.0957562568008705,
      "grad_norm": 0.6685927510261536,
      "learning_rate": 0.0002,
      "loss": 1.2046,
      "step": 11
    },
    {
      "epoch": 0.1044613710554951,
      "grad_norm": 0.7771100997924805,
      "learning_rate": 0.0001980952380952381,
      "loss": 1.0449,
      "step": 12
    },
    {
      "epoch": 0.11316648531011969,
      "grad_norm": 0.8356149196624756,
      "learning_rate": 0.0001961904761904762,
      "loss": 1.1738,
      "step": 13
    },
    {
      "epoch": 0.12187159956474429,
      "grad_norm": 0.865169882774353,
      "learning_rate": 0.0001942857142857143,
      "loss": 1.1387,
      "step": 14
    },
    {
      "epoch": 0.1305767138193689,
      "grad_norm": 0.7983031868934631,
      "learning_rate": 0.0001923809523809524,
      "loss": 1.0069,
      "step": 15
    },
    {
      "epoch": 0.13928182807399347,
      "grad_norm": 0.8247190117835999,
      "learning_rate": 0.00019047619047619048,
      "loss": 1.0478,
      "step": 16
    },
    {
      "epoch": 0.14798694232861806,
      "grad_norm": 0.8784925937652588,
      "learning_rate": 0.00018857142857142857,
      "loss": 1.1615,
      "step": 17
    },
    {
      "epoch": 0.15669205658324264,
      "grad_norm": 0.9426279067993164,
      "learning_rate": 0.0001866666666666667,
      "loss": 1.044,
      "step": 18
    },
    {
      "epoch": 0.16539717083786726,
      "grad_norm": 0.8119654655456543,
      "learning_rate": 0.00018476190476190478,
      "loss": 1.301,
      "step": 19
    },
    {
      "epoch": 0.17410228509249184,
      "grad_norm": 0.7677338123321533,
      "learning_rate": 0.00018285714285714286,
      "loss": 0.9433,
      "step": 20
    },
    {
      "epoch": 0.18280739934711643,
      "grad_norm": 0.7081038355827332,
      "learning_rate": 0.00018095238095238095,
      "loss": 0.9384,
      "step": 21
    },
    {
      "epoch": 0.191512513601741,
      "grad_norm": 0.7553266286849976,
      "learning_rate": 0.00017904761904761907,
      "loss": 1.1745,
      "step": 22
    },
    {
      "epoch": 0.20021762785636563,
      "grad_norm": 0.891456127166748,
      "learning_rate": 0.00017714285714285713,
      "loss": 1.1322,
      "step": 23
    },
    {
      "epoch": 0.2089227421109902,
      "grad_norm": 0.5737559199333191,
      "learning_rate": 0.00017523809523809525,
      "loss": 0.9537,
      "step": 24
    },
    {
      "epoch": 0.2176278563656148,
      "grad_norm": 0.6678743362426758,
      "learning_rate": 0.00017333333333333334,
      "loss": 1.0224,
      "step": 25
    },
    {
      "epoch": 0.22633297062023938,
      "grad_norm": 0.6001664996147156,
      "learning_rate": 0.00017142857142857143,
      "loss": 1.0701,
      "step": 26
    },
    {
      "epoch": 0.235038084874864,
      "grad_norm": 0.6554970741271973,
      "learning_rate": 0.00016952380952380954,
      "loss": 1.2419,
      "step": 27
    },
    {
      "epoch": 0.24374319912948858,
      "grad_norm": 0.5688917636871338,
      "learning_rate": 0.00016761904761904763,
      "loss": 0.8724,
      "step": 28
    },
    {
      "epoch": 0.25244831338411317,
      "grad_norm": 0.6411147713661194,
      "learning_rate": 0.00016571428571428575,
      "loss": 1.0651,
      "step": 29
    },
    {
      "epoch": 0.2611534276387378,
      "grad_norm": 0.6324276924133301,
      "learning_rate": 0.0001638095238095238,
      "loss": 1.1464,
      "step": 30
    },
    {
      "epoch": 0.26985854189336234,
      "grad_norm": 0.6028388142585754,
      "learning_rate": 0.00016190476190476192,
      "loss": 1.0948,
      "step": 31
    },
    {
      "epoch": 0.27856365614798695,
      "grad_norm": 0.6452710032463074,
      "learning_rate": 0.00016,
      "loss": 1.0994,
      "step": 32
    },
    {
      "epoch": 0.28726877040261156,
      "grad_norm": 0.6981925964355469,
      "learning_rate": 0.0001580952380952381,
      "loss": 0.946,
      "step": 33
    },
    {
      "epoch": 0.2959738846572361,
      "grad_norm": 0.6136054396629333,
      "learning_rate": 0.0001561904761904762,
      "loss": 1.014,
      "step": 34
    },
    {
      "epoch": 0.30467899891186073,
      "grad_norm": 0.6166701912879944,
      "learning_rate": 0.0001542857142857143,
      "loss": 1.0725,
      "step": 35
    },
    {
      "epoch": 0.3133841131664853,
      "grad_norm": 0.587670087814331,
      "learning_rate": 0.00015238095238095237,
      "loss": 1.1183,
      "step": 36
    },
    {
      "epoch": 0.3220892274211099,
      "grad_norm": 0.6244456768035889,
      "learning_rate": 0.00015047619047619048,
      "loss": 1.095,
      "step": 37
    },
    {
      "epoch": 0.3307943416757345,
      "grad_norm": 0.624326229095459,
      "learning_rate": 0.00014857142857142857,
      "loss": 1.079,
      "step": 38
    },
    {
      "epoch": 0.3394994559303591,
      "grad_norm": 0.5736309885978699,
      "learning_rate": 0.00014666666666666666,
      "loss": 1.0048,
      "step": 39
    },
    {
      "epoch": 0.3482045701849837,
      "grad_norm": 0.6612578630447388,
      "learning_rate": 0.00014476190476190475,
      "loss": 1.0545,
      "step": 40
    },
    {
      "epoch": 0.35690968443960824,
      "grad_norm": 0.5867776274681091,
      "learning_rate": 0.00014285714285714287,
      "loss": 1.0452,
      "step": 41
    },
    {
      "epoch": 0.36561479869423286,
      "grad_norm": 0.6380172967910767,
      "learning_rate": 0.00014095238095238096,
      "loss": 0.9845,
      "step": 42
    },
    {
      "epoch": 0.37431991294885747,
      "grad_norm": 0.630588173866272,
      "learning_rate": 0.00013904761904761905,
      "loss": 1.1361,
      "step": 43
    },
    {
      "epoch": 0.383025027203482,
      "grad_norm": 0.656988799571991,
      "learning_rate": 0.00013714285714285716,
      "loss": 1.1272,
      "step": 44
    },
    {
      "epoch": 0.39173014145810664,
      "grad_norm": 0.6705630421638489,
      "learning_rate": 0.00013523809523809525,
      "loss": 1.1396,
      "step": 45
    },
    {
      "epoch": 0.40043525571273125,
      "grad_norm": 0.57944655418396,
      "learning_rate": 0.00013333333333333334,
      "loss": 1.05,
      "step": 46
    },
    {
      "epoch": 0.4091403699673558,
      "grad_norm": 0.6325565576553345,
      "learning_rate": 0.00013142857142857143,
      "loss": 1.0114,
      "step": 47
    },
    {
      "epoch": 0.4178454842219804,
      "grad_norm": 0.4821524918079376,
      "learning_rate": 0.00012952380952380954,
      "loss": 0.9478,
      "step": 48
    },
    {
      "epoch": 0.426550598476605,
      "grad_norm": 0.6011167764663696,
      "learning_rate": 0.0001276190476190476,
      "loss": 0.9774,
      "step": 49
    },
    {
      "epoch": 0.4352557127312296,
      "grad_norm": 0.6598947644233704,
      "learning_rate": 0.00012571428571428572,
      "loss": 1.1221,
      "step": 50
    },
    {
      "epoch": 0.4352557127312296,
      "eval_loss": 1.0153025388717651,
      "eval_runtime": 796.9048,
      "eval_samples_per_second": 0.257,
      "eval_steps_per_second": 0.257,
      "step": 50
    },
    {
      "epoch": 0.4439608269858542,
      "grad_norm": 0.5480935573577881,
      "learning_rate": 0.0001238095238095238,
      "loss": 1.2201,
      "step": 51
    },
    {
      "epoch": 0.45266594124047876,
      "grad_norm": 0.6285936236381531,
      "learning_rate": 0.00012190476190476193,
      "loss": 1.0691,
      "step": 52
    },
    {
      "epoch": 0.4613710554951034,
      "grad_norm": 0.6424440145492554,
      "learning_rate": 0.00012,
      "loss": 1.1775,
      "step": 53
    },
    {
      "epoch": 0.470076169749728,
      "grad_norm": 0.5320306420326233,
      "learning_rate": 0.0001180952380952381,
      "loss": 0.9684,
      "step": 54
    },
    {
      "epoch": 0.47878128400435255,
      "grad_norm": 0.5918554663658142,
      "learning_rate": 0.00011619047619047621,
      "loss": 0.9264,
      "step": 55
    },
    {
      "epoch": 0.48748639825897716,
      "grad_norm": 0.5151792168617249,
      "learning_rate": 0.00011428571428571428,
      "loss": 0.9987,
      "step": 56
    },
    {
      "epoch": 0.4961915125136017,
      "grad_norm": 0.5997101664543152,
      "learning_rate": 0.00011238095238095239,
      "loss": 1.0693,
      "step": 57
    },
    {
      "epoch": 0.5048966267682263,
      "grad_norm": 0.5133354067802429,
      "learning_rate": 0.00011047619047619049,
      "loss": 0.9837,
      "step": 58
    },
    {
      "epoch": 0.5136017410228509,
      "grad_norm": 0.694732666015625,
      "learning_rate": 0.00010857142857142856,
      "loss": 1.2468,
      "step": 59
    },
    {
      "epoch": 0.5223068552774756,
      "grad_norm": 0.5531863570213318,
      "learning_rate": 0.00010666666666666667,
      "loss": 1.1677,
      "step": 60
    },
    {
      "epoch": 0.5310119695321001,
      "grad_norm": 0.6390060782432556,
      "learning_rate": 0.00010476190476190477,
      "loss": 1.1446,
      "step": 61
    },
    {
      "epoch": 0.5397170837867247,
      "grad_norm": 0.4926357567310333,
      "learning_rate": 0.00010285714285714286,
      "loss": 1.002,
      "step": 62
    },
    {
      "epoch": 0.5484221980413493,
      "grad_norm": 0.6009288430213928,
      "learning_rate": 0.00010095238095238096,
      "loss": 1.1548,
      "step": 63
    },
    {
      "epoch": 0.5571273122959739,
      "grad_norm": 0.5631808638572693,
      "learning_rate": 9.904761904761905e-05,
      "loss": 1.1203,
      "step": 64
    },
    {
      "epoch": 0.5658324265505985,
      "grad_norm": 0.5474869012832642,
      "learning_rate": 9.714285714285715e-05,
      "loss": 0.94,
      "step": 65
    },
    {
      "epoch": 0.5745375408052231,
      "grad_norm": 0.5298523902893066,
      "learning_rate": 9.523809523809524e-05,
      "loss": 1.0647,
      "step": 66
    },
    {
      "epoch": 0.5832426550598476,
      "grad_norm": 0.5420388579368591,
      "learning_rate": 9.333333333333334e-05,
      "loss": 1.0214,
      "step": 67
    },
    {
      "epoch": 0.5919477693144722,
      "grad_norm": 0.629425585269928,
      "learning_rate": 9.142857142857143e-05,
      "loss": 1.1806,
      "step": 68
    },
    {
      "epoch": 0.6006528835690969,
      "grad_norm": 0.5605244636535645,
      "learning_rate": 8.952380952380953e-05,
      "loss": 1.0508,
      "step": 69
    },
    {
      "epoch": 0.6093579978237215,
      "grad_norm": 0.5545762181282043,
      "learning_rate": 8.761904761904762e-05,
      "loss": 1.0791,
      "step": 70
    },
    {
      "epoch": 0.6180631120783461,
      "grad_norm": 0.5166733860969543,
      "learning_rate": 8.571428571428571e-05,
      "loss": 1.1091,
      "step": 71
    },
    {
      "epoch": 0.6267682263329706,
      "grad_norm": 0.6072342395782471,
      "learning_rate": 8.380952380952382e-05,
      "loss": 1.1921,
      "step": 72
    },
    {
      "epoch": 0.6354733405875952,
      "grad_norm": 0.5810629725456238,
      "learning_rate": 8.19047619047619e-05,
      "loss": 1.076,
      "step": 73
    },
    {
      "epoch": 0.6441784548422198,
      "grad_norm": 0.5930699110031128,
      "learning_rate": 8e-05,
      "loss": 1.0395,
      "step": 74
    },
    {
      "epoch": 0.6528835690968444,
      "grad_norm": 0.5155117511749268,
      "learning_rate": 7.80952380952381e-05,
      "loss": 1.1632,
      "step": 75
    },
    {
      "epoch": 0.661588683351469,
      "grad_norm": 0.6815319061279297,
      "learning_rate": 7.619047619047618e-05,
      "loss": 1.0015,
      "step": 76
    },
    {
      "epoch": 0.6702937976060935,
      "grad_norm": 0.5266006588935852,
      "learning_rate": 7.428571428571429e-05,
      "loss": 1.0115,
      "step": 77
    },
    {
      "epoch": 0.6789989118607181,
      "grad_norm": 0.6500531435012817,
      "learning_rate": 7.238095238095238e-05,
      "loss": 0.8954,
      "step": 78
    },
    {
      "epoch": 0.6877040261153428,
      "grad_norm": 0.5711528062820435,
      "learning_rate": 7.047619047619048e-05,
      "loss": 0.9432,
      "step": 79
    },
    {
      "epoch": 0.6964091403699674,
      "grad_norm": 0.5227874517440796,
      "learning_rate": 6.857142857142858e-05,
      "loss": 1.1526,
      "step": 80
    },
    {
      "epoch": 0.705114254624592,
      "grad_norm": 0.6874245405197144,
      "learning_rate": 6.666666666666667e-05,
      "loss": 1.158,
      "step": 81
    },
    {
      "epoch": 0.7138193688792165,
      "grad_norm": 0.5861294269561768,
      "learning_rate": 6.476190476190477e-05,
      "loss": 1.0479,
      "step": 82
    },
    {
      "epoch": 0.7225244831338411,
      "grad_norm": 0.6131319403648376,
      "learning_rate": 6.285714285714286e-05,
      "loss": 1.1507,
      "step": 83
    },
    {
      "epoch": 0.7312295973884657,
      "grad_norm": 0.6098213791847229,
      "learning_rate": 6.0952380952380964e-05,
      "loss": 1.1744,
      "step": 84
    },
    {
      "epoch": 0.7399347116430903,
      "grad_norm": 0.5993942022323608,
      "learning_rate": 5.904761904761905e-05,
      "loss": 1.0139,
      "step": 85
    },
    {
      "epoch": 0.7486398258977149,
      "grad_norm": 0.6057429313659668,
      "learning_rate": 5.714285714285714e-05,
      "loss": 1.2034,
      "step": 86
    },
    {
      "epoch": 0.7573449401523396,
      "grad_norm": 0.5035505294799805,
      "learning_rate": 5.5238095238095244e-05,
      "loss": 1.0819,
      "step": 87
    },
    {
      "epoch": 0.766050054406964,
      "grad_norm": 0.4878997504711151,
      "learning_rate": 5.333333333333333e-05,
      "loss": 0.935,
      "step": 88
    },
    {
      "epoch": 0.7747551686615887,
      "grad_norm": 0.5962377786636353,
      "learning_rate": 5.142857142857143e-05,
      "loss": 1.0454,
      "step": 89
    },
    {
      "epoch": 0.7834602829162133,
      "grad_norm": 0.6151819825172424,
      "learning_rate": 4.9523809523809525e-05,
      "loss": 0.9445,
      "step": 90
    },
    {
      "epoch": 0.7921653971708379,
      "grad_norm": 0.5197490453720093,
      "learning_rate": 4.761904761904762e-05,
      "loss": 1.0793,
      "step": 91
    },
    {
      "epoch": 0.8008705114254625,
      "grad_norm": 0.5438470840454102,
      "learning_rate": 4.5714285714285716e-05,
      "loss": 0.9505,
      "step": 92
    },
    {
      "epoch": 0.809575625680087,
      "grad_norm": 0.6811717748641968,
      "learning_rate": 4.380952380952381e-05,
      "loss": 1.1097,
      "step": 93
    },
    {
      "epoch": 0.8182807399347116,
      "grad_norm": 0.5593833923339844,
      "learning_rate": 4.190476190476191e-05,
      "loss": 1.0192,
      "step": 94
    },
    {
      "epoch": 0.8269858541893362,
      "grad_norm": 0.5628796219825745,
      "learning_rate": 4e-05,
      "loss": 1.0267,
      "step": 95
    },
    {
      "epoch": 0.8356909684439608,
      "grad_norm": 0.5363481044769287,
      "learning_rate": 3.809523809523809e-05,
      "loss": 0.9162,
      "step": 96
    },
    {
      "epoch": 0.8443960826985855,
      "grad_norm": 0.553103506565094,
      "learning_rate": 3.619047619047619e-05,
      "loss": 1.0066,
      "step": 97
    },
    {
      "epoch": 0.85310119695321,
      "grad_norm": 0.49443262815475464,
      "learning_rate": 3.428571428571429e-05,
      "loss": 0.8951,
      "step": 98
    },
    {
      "epoch": 0.8618063112078346,
      "grad_norm": 0.5097343921661377,
      "learning_rate": 3.2380952380952386e-05,
      "loss": 0.9744,
      "step": 99
    },
    {
      "epoch": 0.8705114254624592,
      "grad_norm": 0.5132281184196472,
      "learning_rate": 3.0476190476190482e-05,
      "loss": 1.1309,
      "step": 100
    },
    {
      "epoch": 0.8705114254624592,
      "eval_loss": 0.9932652711868286,
      "eval_runtime": 796.8493,
      "eval_samples_per_second": 0.257,
      "eval_steps_per_second": 0.257,
      "step": 100
    },
    {
      "epoch": 0.8792165397170838,
      "grad_norm": 0.5541912913322449,
      "learning_rate": 2.857142857142857e-05,
      "loss": 0.9371,
      "step": 101
    },
    {
      "epoch": 0.8879216539717084,
      "grad_norm": 0.6259527802467346,
      "learning_rate": 2.6666666666666667e-05,
      "loss": 1.1663,
      "step": 102
    },
    {
      "epoch": 0.8966267682263329,
      "grad_norm": 0.5261076092720032,
      "learning_rate": 2.4761904761904762e-05,
      "loss": 0.983,
      "step": 103
    },
    {
      "epoch": 0.9053318824809575,
      "grad_norm": 0.6103134751319885,
      "learning_rate": 2.2857142857142858e-05,
      "loss": 1.0757,
      "step": 104
    },
    {
      "epoch": 0.9140369967355821,
      "grad_norm": 0.5596606135368347,
      "learning_rate": 2.0952380952380954e-05,
      "loss": 1.1175,
      "step": 105
    },
    {
      "epoch": 0.9227421109902068,
      "grad_norm": 0.5785785913467407,
      "learning_rate": 1.9047619047619046e-05,
      "loss": 1.1804,
      "step": 106
    },
    {
      "epoch": 0.9314472252448314,
      "grad_norm": 0.6508854031562805,
      "learning_rate": 1.7142857142857145e-05,
      "loss": 1.1522,
      "step": 107
    },
    {
      "epoch": 0.940152339499456,
      "grad_norm": 0.6011777520179749,
      "learning_rate": 1.5238095238095241e-05,
      "loss": 1.1198,
      "step": 108
    },
    {
      "epoch": 0.9488574537540805,
      "grad_norm": 0.5802710056304932,
      "learning_rate": 1.3333333333333333e-05,
      "loss": 1.1232,
      "step": 109
    },
    {
      "epoch": 0.9575625680087051,
      "grad_norm": 0.545036256313324,
      "learning_rate": 1.1428571428571429e-05,
      "loss": 1.1796,
      "step": 110
    },
    {
      "epoch": 0.9662676822633297,
      "grad_norm": 0.5941225290298462,
      "learning_rate": 9.523809523809523e-06,
      "loss": 1.078,
      "step": 111
    },
    {
      "epoch": 0.9749727965179543,
      "grad_norm": 0.5459928512573242,
      "learning_rate": 7.6190476190476205e-06,
      "loss": 0.9992,
      "step": 112
    },
    {
      "epoch": 0.9836779107725789,
      "grad_norm": 0.5767664909362793,
      "learning_rate": 5.7142857142857145e-06,
      "loss": 0.9889,
      "step": 113
    },
    {
      "epoch": 0.9923830250272034,
      "grad_norm": 0.5602152943611145,
      "learning_rate": 3.8095238095238102e-06,
      "loss": 1.2405,
      "step": 114
    },
    {
      "epoch": 1.0,
      "grad_norm": 0.6881780624389648,
      "learning_rate": 1.9047619047619051e-06,
      "loss": 0.9547,
      "step": 115
    }
  ],
  "logging_steps": 1,
  "max_steps": 115,
  "num_input_tokens_seen": 0,
  "num_train_epochs": 1,
  "save_steps": 50,
  "stateful_callbacks": {
    "TrainerControl": {
      "args": {
        "should_epoch_stop": false,
        "should_evaluate": false,
        "should_log": false,
        "should_save": true,
        "should_training_stop": true
      },
      "attributes": {}
    }
  },
  "total_flos": 6031076490823680.0,
  "train_batch_size": 1,
  "trial_name": null,
  "trial_params": null
}
